{
  "type": "FeatureCollection",
  "features": [
    {
      "type": "Feature",
      "properties": {
        "id": "HR-PILLAR-001",
        "village": "Morni",
        "district": "Panchkula",
        "survey_date": "2026-02-10",
        "survey_no": "MOR/2026/001",
        "status": "Verified",
        "image_url": "/pillar-placeholder.svg"
      },
      "geometry": { "type": "Point", "coordinates": [76.818, 30.822] }
    },
    {
      "type": "Feature",
      "properties": {
        "id": "HR-PILLAR-002",
        "village": "Pinjore",
        "district": "Panchkula",
        "survey_date": "2026-02-11",
        "survey_no": "PIN/2026/002",
        "status": "Verified",
        "image_url": "/pillar-placeholder.svg"
      },
      "geometry": { "type": "Point", "coordinates": [76.904, 30.867] }
    },
    {
      "type": "Feature",
      "properties": {
        "id": "HR-PILLAR-003",
        "village": "Kalka",
        "district": "Panchkula",
        "survey_date": "2026-02-12",
        "survey_no": "KAL/2026/003",
        "status": "Verified",
        "image_url": "/pillar-placeholder.svg"
      },
      "geometry": { "type": "Point", "coordinates": [76.982, 30.824] }
    },
    {
      "type": "Feature",
      "properties": {
        "id": "HR-PILLAR-004",
        "village": "Morni",
        "district": "Panchkula",
        "survey_date": "2026-02-14",
        "survey_no": "MOR/2026/004",
        "status": "Verified",
        "image_url": "/pillar-placeholder.svg"
      },
      "geometry": { "type": "Point", "coordinates": [76.968, 30.731] }
    },
    {
      "type": "Feature",
      "properties": {
        "id": "HR-PILLAR-005",
        "village": "Morni",
        "district": "Panchkula",
        "survey_date": "2026-02-15",
        "survey_no": "MOR/2026/005",
        "status": "Verified",
        "image_url": "/pillar-placeholder.svg"
      },
      "geometry": { "type": "Point", "coordinates": [76.868, 30.711] }
    },
    {
      "type": "Feature",
      "properties": {
        "id": "HR-PILLAR-006",
        "village": "Morni",
        "district": "Panchkula",
        "survey_date": "2026-02-16",
        "survey_no": "MOR/2026/006",
        "status": "Verified",
        "image_url": "/pillar-placeholder.svg"
      },
      "geometry": { "type": "Point", "coordinates": [76.81, 30.761] }
    },
    {
      "type": "Feature",
      "properties": {
        "id": "HR-PILLAR-007",
        "village": "Pinjore",
        "district": "Panchkula",
        "survey_date": "2026-02-18",
        "survey_no": "PIN/2026/007",
        "status": "Verified",
        "image_url": "/pillar-placeholder.svg"
      },
      "geometry": { "type": "Point", "coordinates": [76.861, 30.833] }
    },
    {
      "type": "Feature",
      "properties": {
        "id": "HR-PILLAR-008",
        "village": "Kalka",
        "district": "Panchkula",
        "survey_date": "2026-02-19",
        "survey_no": "KAL/2026/008",
        "status": "Verified",
        "image_url": "/pillar-placeholder.svg"
      },
      "geometry": { "type": "Point", "coordinates": [77.007, 30.835] }
    },
    {
      "type": "Feature",
      "properties": {
        "id": "HR-PILLAR-009",
        "village": "Kalka",
        "district": "Panchkula",
        "survey_date": "2026-02-21",
        "survey_no": "KAL/2026/009",
        "status": "Verified",
        "image_url": "/pillar-placeholder.svg"
      },
      "geometry": { "type": "Point", "coordinates": [77.035, 30.748] }
    },
    {
      "type": "Feature",
      "properties": {
        "id": "HR-PILLAR-010",
        "village": "Morni",
        "district": "Panchkula",
        "survey_date": "2026-02-22",
        "survey_no": "MOR/2026/010",
        "status": "Verified",
        "image_url": "/pillar-placeholder.svg"
      },
      "geometry": { "type": "Point", "coordinates": [76.938, 30.688] }
    },
    {
      "type": "Feature",
      "properties": {
        "id": "HR-PILLAR-011",
        "village": "Morni",
        "district": "Panchkula",
        "survey_date": "2026-02-24",
        "survey_no": "MOR/2026/011",
        "status": "Verified",
        "image_url": "/pillar-placeholder.svg"
      },
      "geometry": { "type": "Point", "coordinates": [76.838, 30.734] }
    }
  ]
}
